meta_nbextension-0.1.1.data/data/etc/jupyter/nbconfig/notebook.d/nbmeta.json
meta_nbextension-0.1.1.data/data/share/jupyter/nbextensions/nbmeta/nbmeta.js
nbmeta/__init__.py
nbmeta/static/nbmeta.js
meta_nbextension-0.1.1.dist-info/METADATA
meta_nbextension-0.1.1.dist-info/WHEEL
meta_nbextension-0.1.1.dist-info/top_level.txt
meta_nbextension-0.1.1.dist-info/RECORD
