Metadata-Version: 2.1
Name: meta-nbextension
Version: 0.1.1
Summary: Access to current notebook and cell in an nbclassic notebook
Home-page: https://github.com/answerdotai/meta-nbextension
Author: Jeremy Howard
Author-email: info@fast.ai
License: Apache License 2.0
Classifier: Programming Language :: Python :: 3
Classifier: License :: OSI Approved :: Apache Software License
Classifier: Operating System :: OS Independent
Classifier: Framework :: Jupyter
Classifier: Intended Audience :: Developers
Classifier: Intended Audience :: Science/Research
Classifier: Topic :: Software Development
Classifier: Topic :: Scientific/Engineering
Requires-Python: >=3.6
Requires-Dist: notebook <7
